MANIFEST.in
README
csr_ha.service
debug_ha.sh
ha_tools.sh
setup.cfg
setup.py
validate.py
csr_ha/__init__.py
csr_ha.egg-info/PKG-INFO
csr_ha.egg-info/SOURCES.txt
csr_ha.egg-info/dependency_links.txt
csr_ha.egg-info/requires.txt
csr_ha.egg-info/top_level.txt
csr_ha/client_api/__init__.py
csr_ha/client_api/clear_params.py
csr_ha/client_api/create_node.py
csr_ha/client_api/delete_node.py
csr_ha/client_api/ha_api.py
csr_ha/client_api/node_event.py
csr_ha/client_api/py_caller.py
csr_ha/client_api/revert_nodes.sh
csr_ha/client_api/set_params.py
csr_ha/client_api/show_node.py
csr_ha/server/__init__.py
csr_ha/server/event_mgr.py
csr_ha/server/ha_server.py
csr_ha/server/node_mgr.py