Metadata-Version: 1.1
Name: csr-ha
Version: 2.0.2
Summary: High availability of CSR 1000v routers in cloud
Home-page: https://github4-chn.cisco.com/csr1000v-cloud/csr_ha
Author: Cisco Systems Inc.
Author-email: csr-cloud-dev@cisco.com
License: MIT
Download-URL: https://github4-chn.cisco.com/csr1000v-cloud/csr_ha/archive/2.0.2.tar.gz
Keywords: cisco,ha,high availability,csr1000v,csr,guestshell
Platform: UNKNOWN
Classifier: Development Status :: 3 - Alpha
Classifier: Intended Audience :: Developers
Classifier: License :: OSI Approved :: MIT License
Classifier: Programming Language :: Python :: 2.7
Classifier: Programming Language :: Python :: 3.6
